{
  "template": true,
  "opCatString": "bbidadbanbqdnadardbbqbbqdbt",
  "opCatFreq": [
    4,
    9,
    0,
    6,
    0,
    0,
    0,
    0,
    1,
    0,
    0,
    0,
    0,
    2,
    0,
    0,
    3,
    1,
    0,
    1,
    0
  ],
  "labelMap": {
    "L2015744690": 62,
    "L1171672119": 18,
    "L1759969037": 251,
    "L2131361171": 198,
    "L549041464": 435,
    "L359851081": 293,
    "L2040919865": 134,
    "L2654289": 470,
    "L2066473405": 91,
    "L703168415": 358,
    "L2112978551": 220
  }
}