{
  "L102 0 167 goto L788223665": [
    "L227 0 21 iload 5",
    "L227 1 25 aload 1",
    "L227 2 190 arraylength",
    "L227 3 161 if_icmplt L1996002959"
  ],
  "L116 0 25 aload 1": [
    "L116 2 46 iaload"
  ],
  "L116 1 21 iload 5": [
    "L116 2 46 iaload"
  ],
  "L116 2 46 iaload": [
    "L116 6 162 if_icmpge L979682126"
  ],
  "L116 3 25 aload 1": [
    "L116 5 46 iaload"
  ],
  "L116 4 21 iload 4": [
    "L116 5 46 iaload"
  ],
  "L116 5 46 iaload": [
    "L116 6 162 if_icmpge L979682126"
  ],
  "L116 6 162 if_icmpge L979682126": [
    "L116 7 21 iload 5",
    "L116 8 54 istore 4",
    "L214 0 132 iinc 5",
    "L227 0 21 iload 5",
    "L227 1 25 aload 1",
    "L227 2 190 arraylength",
    "L227 3 161 if_icmplt L1996002959"
  ],
  "L116 7 21 iload 5": [
    "L116 8 54 istore 4"
  ],
  "L116 8 54 istore 4": [
    "L116 4 21 iload 4",
    "L314 3 21 iload 4",
    "L375 1 21 iload 4"
  ],
  "L214 0 132 iinc 5": [
    "L116 1 21 iload 5",
    "L116 7 21 iload 5",
    "L227 0 21 iload 5"
  ],
  "L227 0 21 iload 5": [
    "L227 3 161 if_icmplt L1996002959"
  ],
  "L227 1 25 aload 1": [
    "L227 2 190 arraylength"
  ],
  "L227 2 190 arraylength": [
    "L227 3 161 if_icmplt L1996002959"
  ],
  "L227 3 161 if_icmplt L1996002959": [
    "L116 0 25 aload 1",
    "L116 1 21 iload 5",
    "L116 2 46 iaload",
    "L116 3 25 aload 1",
    "L116 4 21 iload 4",
    "L116 5 46 iaload",
    "L116 6 162 if_icmpge L979682126",
    "L273 0 25 aload 1",
    "L273 1 21 iload 3",
    "L273 2 46 iaload",
    "L273 3 54 istore 5",
    "L314 0 25 aload 1",
    "L314 1 21 iload 3",
    "L314 2 25 aload 1",
    "L314 3 21 iload 4",
    "L314 4 46 iaload",
    "L314 5 79 iastore",
    "L375 0 25 aload 1",
    "L375 1 21 iload 4",
    "L375 2 21 iload 5",
    "L375 3 79 iastore",
    "L417 0 132 iinc 3",
    "L430 0 21 iload 3",
    "L430 1 25 aload 1",
    "L430 2 190 arraylength",
    "L430 3 4 iconst_1",
    "L430 4 100 isub",
    "L430 5 161 if_icmplt L1459992991"
  ],
  "L27 0 167 goto L1254691612": [
    "L430 0 21 iload 3",
    "L430 1 25 aload 1",
    "L430 2 190 arraylength",
    "L430 3 4 iconst_1",
    "L430 4 100 isub",
    "L430 5 161 if_icmplt L1459992991"
  ],
  "L273 0 25 aload 1": [
    "L273 2 46 iaload"
  ],
  "L273 1 21 iload 3": [
    "L273 2 46 iaload"
  ],
  "L273 2 46 iaload": [
    "L273 3 54 istore 5"
  ],
  "L273 3 54 istore 5": [
    "L375 2 21 iload 5"
  ],
  "L314 0 25 aload 1": [
    "L314 5 79 iastore"
  ],
  "L314 1 21 iload 3": [
    "L314 5 79 iastore"
  ],
  "L314 2 25 aload 1": [
    "L314 4 46 iaload"
  ],
  "L314 3 21 iload 4": [
    "L314 4 46 iaload"
  ],
  "L314 4 46 iaload": [
    "L314 5 79 iastore"
  ],
  "L375 0 25 aload 1": [
    "L375 3 79 iastore"
  ],
  "L375 1 21 iload 4": [
    "L375 3 79 iastore"
  ],
  "L375 2 21 iload 5": [
    "L375 3 79 iastore"
  ],
  "L41 0 21 iload 3": [
    "L41 1 54 istore 4"
  ],
  "L41 1 54 istore 4": [
    "L116 4 21 iload 4",
    "L314 3 21 iload 4",
    "L375 1 21 iload 4"
  ],
  "L417 0 132 iinc 3": [
    "L273 1 21 iload 3",
    "L314 1 21 iload 3",
    "L41 0 21 iload 3",
    "L430 0 21 iload 3",
    "L62 0 21 iload 3"
  ],
  "L430 0 21 iload 3": [
    "L430 5 161 if_icmplt L1459992991"
  ],
  "L430 1 25 aload 1": [
    "L430 2 190 arraylength"
  ],
  "L430 2 190 arraylength": [
    "L430 4 100 isub"
  ],
  "L430 3 4 iconst_1": [
    "L430 4 100 isub"
  ],
  "L430 4 100 isub": [
    "L430 5 161 if_icmplt L1459992991"
  ],
  "L430 5 161 if_icmplt L1459992991": [
    "L102 0 167 goto L788223665",
    "L41 0 21 iload 3",
    "L41 1 54 istore 4",
    "L494 0 177 return",
    "L62 0 21 iload 3",
    "L62 1 4 iconst_1",
    "L62 2 96 iadd",
    "L62 3 54 istore 5"
  ],
  "L62 0 21 iload 3": [
    "L62 2 96 iadd"
  ],
  "L62 1 4 iconst_1": [
    "L62 2 96 iadd"
  ],
  "L62 2 96 iadd": [
    "L62 3 54 istore 5"
  ],
  "L62 3 54 istore 5": [
    "L116 1 21 iload 5",
    "L116 7 21 iload 5",
    "L227 0 21 iload 5"
  ],
  "L8 0 3 iconst_0": [
    "L8 1 54 istore 3"
  ],
  "L8 1 54 istore 3": [
    "L273 1 21 iload 3",
    "L314 1 21 iload 3",
    "L41 0 21 iload 3",
    "L430 0 21 iload 3",
    "L62 0 21 iload 3"
  ]
}